matchable/__init__.py
matchable/exceptions.py
matchable/match.py
matchable/spec.py
matchable-0.1.2.dist-info/LICENSE
matchable-0.1.2.dist-info/WHEEL
matchable-0.1.2.dist-info/METADATA
matchable-0.1.2.dist-info/RECORD
