Metadata-Version: 2.1
Name: matchable
Version: 0.1.2
Summary: Attribute-based object matching
Home-page: https://github.com/Dominik1123/matchable
License: MIT
Keywords: pattern,matching,pattern matching
Author: Dominik1123
Requires-Python: >=3.7,<4.0
Classifier: License :: OSI Approved :: MIT License
Classifier: Programming Language :: Python :: 3
Classifier: Programming Language :: Python :: 3.7
Classifier: Programming Language :: Python :: 3.8
Requires-Dist: importlib_metadata (>=1.6.1,<2.0.0); python_version < "3.8"
Requires-Dist: typing_extensions (>=3.7.4,<4.0.0); python_version < "3.8"
Project-URL: Repository, https://github.com/Dominik1123/matchable
